mypackage696969696969/__init__.py
mypackage696969696969/decorators.py
mypackage696969696969/descriptors.py
mypackage696969696969/generators.py
mypackage696969696969/iterators.py
mypackage696969696969-0.1.dist-info/METADATA
mypackage696969696969-0.1.dist-info/WHEEL
mypackage696969696969-0.1.dist-info/top_level.txt
mypackage696969696969-0.1.dist-info/RECORD
